aws_razor/__init__.py
aws_razor/main.py
aws_razor-2.27.45.dist-info/METADATA
aws_razor-2.27.45.dist-info/WHEEL
aws_razor-2.27.45.dist-info/entry_points.txt
aws_razor-2.27.45.dist-info/RECORD
