Metadata-Version: 2.4
Name: aws-razor
Version: 2.27.45
Summary: Alternative CLI frontend for aws-cli completions
Project-URL: homepage, https://github.com/dead10ck/aws-razor
Author-email: Skyler Hawthorne <skyler@dead10ck.dev>
License-Expression: MPL-2.0
Classifier: Intended Audience :: Developers
Classifier: Intended Audience :: System Administrators
Classifier: Natural Language :: English
Classifier: Programming Language :: Python
Classifier: Programming Language :: Python :: 3
Classifier: Programming Language :: Python :: 3 :: Only
Classifier: Programming Language :: Python :: 3.8
Classifier: Programming Language :: Python :: 3.9
Classifier: Programming Language :: Python :: 3.10
Classifier: Programming Language :: Python :: 3.11
Classifier: Programming Language :: Python :: 3.12
Requires-Python: >=3.9
Requires-Dist: awscli>=2.25.4
